{"id":"j95xd7tjl2d4vmcvnqfhkjz","title":"Angular","desc":"","updated":1668223274483,"created":1533453322000,"custom":{},"fname":"dev.fe.angular","type":"note","vault":{"fsPath":".","selfContained":true,"name":"Dendron"},"contentHash":"87af52fe28b72728bc3b3bc69b70c98d","links":[],"anchors":{"개요":{"type":"header","text":"개요","value":"개요","line":8,"column":0,"depth":2},"참고-자료":{"type":"header","text":"참고 자료","value":"참고-자료","line":55,"column":0,"depth":2}},"children":[],"parent":"yq2839iijurmzkrwkqwo9ps","data":{}}
