{"id":"rfaecb1r4pxpahsrighqpfi","title":"Dev","desc":"","updated":1666489926104,"created":1666489926104,"custom":{"nav_order":0,"permalink":"/"},"fname":"dev","type":"note","vault":{"fsPath":".","selfContained":true,"name":"Dendron"},"contentHash":"5f3d9b993bc1c60c0e10119b00a45c49","links":[],"anchors":{},"children":["vmcgt1bw13lwsobet50r3vl","pj0dbesw2qm5j1tub9f34pg","e40hlh2wukm75vo4t8r9c7p","7xwnx64er01irhu8wg1q5zm","4buyekecqhzdg87aqxmh1rz","n1xmefdyaaztqb8wmsmqtjj","d8p9jq81rc0pfbbuzz7prah","yq2839iijurmzkrwkqwo9ps","51sfhirev9l2r8bef9utfb9","xuw6kyksesfaatsmt3gctyi","njc2zpmxz8izls7ogwdj20h","d3ma1d2r59fhejrl6bn9g0e","tgd9pt1fu1j4ejm4g09vlx4","5jlkrg4hx6dpy5tr55grkh6","ockg1gb78gpshwty5zjmvue","owsm2ti22dslhpk9oduhhku","52x2zgp7jpygai1h0jpv0t8","2d5oqog2rsdfdogne54tq9t"],"parent":null,"data":{}}
